odoo/addons/stock_picking_invoicing_incoterm/README.rst
odoo/addons/stock_picking_invoicing_incoterm/__init__.py
odoo/addons/stock_picking_invoicing_incoterm/__manifest__.py
odoo/addons/stock_picking_invoicing_incoterm/i18n/es.po
odoo/addons/stock_picking_invoicing_incoterm/i18n/it.po
odoo/addons/stock_picking_invoicing_incoterm/i18n/stock_picking_invoicing_incoterm.pot
odoo/addons/stock_picking_invoicing_incoterm/models/__init__.py
odoo/addons/stock_picking_invoicing_incoterm/models/stock.py
odoo/addons/stock_picking_invoicing_incoterm/static/description/icon.png
odoo/addons/stock_picking_invoicing_incoterm/views/stock_picking_views.xml
odoo_addon_stock_picking_invoicing_incoterm-15.0.1.0.0.5.dist-info/METADATA
odoo_addon_stock_picking_invoicing_incoterm-15.0.1.0.0.5.dist-info/WHEEL
odoo_addon_stock_picking_invoicing_incoterm-15.0.1.0.0.5.dist-info/top_level.txt
odoo_addon_stock_picking_invoicing_incoterm-15.0.1.0.0.5.dist-info/RECORD
